CHANGES.rst
CONTRIBUTORS.rst
MANIFEST.in
README.rst
setup.cfg
setup.py
docs/LICENSE.GPL
docs/LICENSE.rst
docs/index.rst
src/collective/__init__.py
src/collective.document_hide_summary.egg-info/PKG-INFO
src/collective.document_hide_summary.egg-info/SOURCES.txt
src/collective.document_hide_summary.egg-info/dependency_links.txt
src/collective.document_hide_summary.egg-info/entry_points.txt
src/collective.document_hide_summary.egg-info/namespace_packages.txt
src/collective.document_hide_summary.egg-info/not-zip-safe
src/collective.document_hide_summary.egg-info/requires.txt
src/collective.document_hide_summary.egg-info/top_level.txt
src/collective/document_hide_summary/__init__.py
src/collective/document_hide_summary/configure.zcml
src/collective/document_hide_summary/interfaces.py
src/collective/document_hide_summary/setuphandlers.py
src/collective/document_hide_summary/testing.py
src/collective/document_hide_summary/browser/__init__.py
src/collective/document_hide_summary/browser/configure.zcml
src/collective/document_hide_summary/browser/overrides/.gitkeep
src/collective/document_hide_summary/browser/static/.gitkeep
src/collective/document_hide_summary/browser/templates/document_hide_description.pt
src/collective/document_hide_summary/browser/templates/document_hide_title.pt
src/collective/document_hide_summary/browser/templates/document_hide_title_and_description.pt
src/collective/document_hide_summary/locales/collective.document_view_hide_summary.pot
src/collective/document_hide_summary/locales/update.sh
src/collective/document_hide_summary/profiles/default/browserlayer.xml
src/collective/document_hide_summary/profiles/default/metadata.xml
src/collective/document_hide_summary/profiles/default/registry.xml
src/collective/document_hide_summary/profiles/default/types.xml
src/collective/document_hide_summary/profiles/default/types/Document.xml
src/collective/document_hide_summary/profiles/uninstall/browserlayer.xml
src/collective/document_hide_summary/profiles/uninstall/types/Document.xml
src/collective/document_hide_summary/tests/__init__.py
src/collective/document_hide_summary/tests/test_robot.py
src/collective/document_hide_summary/tests/test_setup.py
src/collective/document_hide_summary/tests/robot/test_example.robot