Metadata-Version: 1.1
Name: collective.document-hide-summary
Version: 1.1.1
Summary: An add-on for Plone that lets you hide a Document's title, summary (description), or both
Home-page: https://pypi.python.org/pypi/collective.document_hide_summary
Author: T. Kim Nguyen
Author-email: kim.nguyen@wildcardcorp.com
License: GPL version 2
Keywords: Python Plone
Platform: UNKNOWN
Classifier: Environment :: Web Environment
Classifier: Framework :: Plone
Classifier: Framework :: Plone :: 5.1
Classifier: Programming Language :: Python
Classifier: Programming Language :: Python :: 2.7
Classifier: Operating System :: OS Independent
Classifier: License :: OSI Approved :: GNU General Public License v2 (GPLv2)
